<?xml version="1.0" encoding="UTF-8"?>
<con:soapui-project id="d84b9524-7725-4bcb-908e-f4adad5d2796" activeEnvironment="Default" name="LocalHostEmp" soapui-version="5.5.0" abortOnError="false" runType="SEQUENTIAL" resourceRoot="" xmlns:con="http://eviware.com/soapui/config"><con:settings/><con:interface xsi:type="con:WsdlInterface" id="bc3524d7-4b79-4831-b97c-9d6e7c39c7e8" wsaVersion="NONE" name="EmployeeManagementServiceSoap12Binding" type="wsdl" bindingName="{http://sample.com/reservation/guest}EmployeeManagementServiceSoap12Binding" soapVersion="1_2" anonymous="optional" definition="http://localhost:8082/axis2/services/EmployeeManagementService?wsdl" xmlns:xsi="http://www.w3.org/2001/XMLSchema-instance"><con:settings/><con:definitionCache type="TEXT" rootPart="http://localhost:8082/axis2/services/EmployeeManagementService?wsdl"><con:part><con:url>http://localhost:8082/axis2/services/EmployeeManagementService?wsdl</con:url><con:content><![CDATA[<wsdl:definitions targetNamespace="http://sample.com/reservation/guest" xmlns:wsdl="http://schemas.xmlsoap.org/wsdl/" xmlns:ns="http://sample.com/reservation/guest/types" xmlns:wsaw="http://www.w3.org/2006/05/addressing/wsdl" xmlns:mime="http://schemas.xmlsoap.org/wsdl/mime/" xmlns:tns="http://sample.com/reservation/guest" xmlns:http="http://schemas.xmlsoap.org/wsdl/http/" xmlns:xs="http://www.w3.org/2001/XMLSchema" xmlns:ax21="http://exception.reservation.sample.com/xsd" xmlns:soap12="http://schemas.xmlsoap.org/wsdl/soap12/" xmlns:ns1="http://org.apache.axis2/xsd" xmlns:soap="http://schemas.xmlsoap.org/wsdl/soap/">
  <wsdl:documentation>EmployeeManagementService</wsdl:documentation>
  <wsdl:types>
    <xs:schema attributeFormDefault="qualified" elementFormDefault="qualified" targetNamespace="http://exception.reservation.sample.com/xsd">
      <xs:complexType name="EmployeeManagementException">
        <xs:sequence>
          <xs:element minOccurs="0" name="message" nillable="true" type="xs:string"/>
        </xs:sequence>
      </xs:complexType>
    </xs:schema>
    <xs:schema attributeFormDefault="qualified" elementFormDefault="qualified" targetNamespace="http://sample.com/reservation/guest/types" xmlns:ax22="http://exception.reservation.sample.com/xsd">
      <xs:import namespace="http://exception.reservation.sample.com/xsd"/>
      <xs:element name="EmployeeManagementServiceEmployeeManagementException">
        <xs:complexType>
          <xs:sequence>
            <xs:element minOccurs="0" name="EmployeeManagementException" nillable="true" type="ax22:EmployeeManagementException"/>
          </xs:sequence>
        </xs:complexType>
      </xs:element>
      <xs:element name="addEmployee">
        <xs:complexType>
          <xs:sequence>
            <xs:element minOccurs="0" name="name" nillable="true" type="xs:string"/>
            <xs:element minOccurs="0" name="id" nillable="true" type="xs:string"/>
            <xs:element minOccurs="0" name="Department" nillable="true" type="xs:string"/>
            <xs:element minOccurs="0" name="age" type="xs:int"/>
          </xs:sequence>
        </xs:complexType>
      </xs:element>
      <xs:element name="addEmployeeResponse">
        <xs:complexType>
          <xs:sequence>
            <xs:element minOccurs="0" name="return" type="xs:boolean"/>
          </xs:sequence>
        </xs:complexType>
      </xs:element>
      <xs:element name="deleteEmployee">
        <xs:complexType>
          <xs:sequence>
            <xs:element minOccurs="0" name="employeeName" nillable="true" type="xs:string"/>
          </xs:sequence>
        </xs:complexType>
      </xs:element>
      <xs:element name="getEmployeeDetails">
        <xs:complexType>
          <xs:sequence>
            <xs:element minOccurs="0" name="employeeName" nillable="true" type="xs:string"/>
          </xs:sequence>
        </xs:complexType>
      </xs:element>
      <xs:element name="getEmployeeDetailsResponse">
        <xs:complexType>
          <xs:sequence>
            <xs:element minOccurs="0" name="return" nillable="true" type="ns:Employee"/>
          </xs:sequence>
        </xs:complexType>
      </xs:element>
      <xs:complexType name="Employee">
        <xs:sequence>
          <xs:element minOccurs="0" name="age" type="xs:int"/>
          <xs:element minOccurs="0" name="department" nillable="true" type="xs:string"/>
          <xs:element minOccurs="0" name="id" nillable="true" type="xs:string"/>
          <xs:element minOccurs="0" name="name" nillable="true" type="xs:string"/>
        </xs:sequence>
      </xs:complexType>
    </xs:schema>
  </wsdl:types>
  <wsdl:message name="getEmployeeDetailsRequest">
    <wsdl:part name="parameters" element="ns:getEmployeeDetails"/>
  </wsdl:message>
  <wsdl:message name="getEmployeeDetailsResponse">
    <wsdl:part name="parameters" element="ns:getEmployeeDetailsResponse"/>
  </wsdl:message>
  <wsdl:message name="EmployeeManagementServiceEmployeeManagementException">
    <wsdl:part name="parameters" element="ns:EmployeeManagementServiceEmployeeManagementException"/>
  </wsdl:message>
  <wsdl:message name="deleteEmployeeRequest">
    <wsdl:part name="parameters" element="ns:deleteEmployee"/>
  </wsdl:message>
  <wsdl:message name="addEmployeeRequest">
    <wsdl:part name="parameters" element="ns:addEmployee"/>
  </wsdl:message>
  <wsdl:message name="addEmployeeResponse">
    <wsdl:part name="parameters" element="ns:addEmployeeResponse"/>
  </wsdl:message>
  <wsdl:portType name="EmployeeManagementServicePortType">
    <wsdl:operation name="getEmployeeDetails">
      <wsdl:input message="tns:getEmployeeDetailsRequest" wsaw:Action="urn:getEmployeeDetails"/>
      <wsdl:output message="tns:getEmployeeDetailsResponse" wsaw:Action="urn:getEmployeeDetailsResponse"/>
      <wsdl:fault message="tns:EmployeeManagementServiceEmployeeManagementException" name="EmployeeManagementServiceEmployeeManagementException" wsaw:Action="urn:getEmployeeDetailsEmployeeManagementServiceEmployeeManagementException"/>
    </wsdl:operation>
    <wsdl:operation name="deleteEmployee">
      <wsdl:input message="tns:deleteEmployeeRequest" wsaw:Action="urn:deleteEmployee"/>
      <wsdl:fault message="tns:EmployeeManagementServiceEmployeeManagementException" name="EmployeeManagementServiceEmployeeManagementException" wsaw:Action="urn:deleteEmployeeEmployeeManagementServiceEmployeeManagementException"/>
    </wsdl:operation>
    <wsdl:operation name="addEmployee">
      <wsdl:input message="tns:addEmployeeRequest" wsaw:Action="urn:addEmployee"/>
      <wsdl:output message="tns:addEmployeeResponse" wsaw:Action="urn:addEmployeeResponse"/>
      <wsdl:fault message="tns:EmployeeManagementServiceEmployeeManagementException" name="EmployeeManagementServiceEmployeeManagementException" wsaw:Action="urn:addEmployeeEmployeeManagementServiceEmployeeManagementException"/>
    </wsdl:operation>
  </wsdl:portType>
  <wsdl:binding name="EmployeeManagementServiceSoap11Binding" type="tns:EmployeeManagementServicePortType">
    <soap:binding transport="http://schemas.xmlsoap.org/soap/http" style="document"/>
    <wsdl:operation name="getEmployeeDetails">
      <soap:operation soapAction="urn:getEmployeeDetails" style="document"/>
      <wsdl:input>
        <soap:body use="literal"/>
      </wsdl:input>
      <wsdl:output>
        <soap:body use="literal"/>
      </wsdl:output>
      <wsdl:fault name="EmployeeManagementServiceEmployeeManagementException">
        <soap:fault use="literal" name="EmployeeManagementServiceEmployeeManagementException"/>
      </wsdl:fault>
    </wsdl:operation>
    <wsdl:operation name="deleteEmployee">
      <soap:operation soapAction="urn:deleteEmployee" style="document"/>
      <wsdl:input>
        <soap:body use="literal"/>
      </wsdl:input>
      <wsdl:fault name="EmployeeManagementServiceEmployeeManagementException">
        <soap:fault use="literal" name="EmployeeManagementServiceEmployeeManagementException"/>
      </wsdl:fault>
    </wsdl:operation>
    <wsdl:operation name="addEmployee">
      <soap:operation soapAction="urn:addEmployee" style="document"/>
      <wsdl:input>
        <soap:body use="literal"/>
      </wsdl:input>
      <wsdl:output>
        <soap:body use="literal"/>
      </wsdl:output>
      <wsdl:fault name="EmployeeManagementServiceEmployeeManagementException">
        <soap:fault use="literal" name="EmployeeManagementServiceEmployeeManagementException"/>
      </wsdl:fault>
    </wsdl:operation>
  </wsdl:binding>
  <wsdl:binding name="EmployeeManagementServiceSoap12Binding" type="tns:EmployeeManagementServicePortType">
    <soap12:binding transport="http://schemas.xmlsoap.org/soap/http" style="document"/>
    <wsdl:operation name="getEmployeeDetails">
      <soap12:operation soapAction="urn:getEmployeeDetails" style="document"/>
      <wsdl:input>
        <soap12:body use="literal"/>
      </wsdl:input>
      <wsdl:output>
        <soap12:body use="literal"/>
      </wsdl:output>
      <wsdl:fault name="EmployeeManagementServiceEmployeeManagementException">
        <soap12:fault use="literal" name="EmployeeManagementServiceEmployeeManagementException"/>
      </wsdl:fault>
    </wsdl:operation>
    <wsdl:operation name="deleteEmployee">
      <soap12:operation soapAction="urn:deleteEmployee" style="document"/>
      <wsdl:input>
        <soap12:body use="literal"/>
      </wsdl:input>
      <wsdl:fault name="EmployeeManagementServiceEmployeeManagementException">
        <soap12:fault use="literal" name="EmployeeManagementServiceEmployeeManagementException"/>
      </wsdl:fault>
    </wsdl:operation>
    <wsdl:operation name="addEmployee">
      <soap12:operation soapAction="urn:addEmployee" style="document"/>
      <wsdl:input>
        <soap12:body use="literal"/>
      </wsdl:input>
      <wsdl:output>
        <soap12:body use="literal"/>
      </wsdl:output>
      <wsdl:fault name="EmployeeManagementServiceEmployeeManagementException">
        <soap12:fault use="literal" name="EmployeeManagementServiceEmployeeManagementException"/>
      </wsdl:fault>
    </wsdl:operation>
  </wsdl:binding>
  <wsdl:binding name="EmployeeManagementServiceHttpBinding" type="tns:EmployeeManagementServicePortType">
    <http:binding verb="POST"/>
    <wsdl:operation name="getEmployeeDetails">
      <http:operation location="getEmployeeDetails"/>
      <wsdl:input>
        <mime:content type="application/xml" part="parameters"/>
      </wsdl:input>
      <wsdl:output>
        <mime:content type="application/xml" part="parameters"/>
      </wsdl:output>
    </wsdl:operation>
    <wsdl:operation name="deleteEmployee">
      <http:operation location="deleteEmployee"/>
      <wsdl:input>
        <mime:content type="application/xml" part="parameters"/>
      </wsdl:input>
    </wsdl:operation>
    <wsdl:operation name="addEmployee">
      <http:operation location="addEmployee"/>
      <wsdl:input>
        <mime:content type="application/xml" part="parameters"/>
      </wsdl:input>
      <wsdl:output>
        <mime:content type="application/xml" part="parameters"/>
      </wsdl:output>
    </wsdl:operation>
  </wsdl:binding>
  <wsdl:service name="EmployeeManagementService">
    <wsdl:port name="EmployeeManagementServiceHttpSoap11Endpoint" binding="tns:EmployeeManagementServiceSoap11Binding">
      <soap:address location="http://localhost:8082/axis2/services/EmployeeManagementService.EmployeeManagementServiceHttpSoap11Endpoint/"/>
    </wsdl:port>
    <wsdl:port name="EmployeeManagementServiceHttpSoap12Endpoint" binding="tns:EmployeeManagementServiceSoap12Binding">
      <soap12:address location="http://localhost:8082/axis2/services/EmployeeManagementService.EmployeeManagementServiceHttpSoap12Endpoint/"/>
    </wsdl:port>
    <wsdl:port name="EmployeeManagementServiceHttpEndpoint" binding="tns:EmployeeManagementServiceHttpBinding">
      <http:address location="http://localhost:8082/axis2/services/EmployeeManagementService.EmployeeManagementServiceHttpEndpoint/"/>
    </wsdl:port>
  </wsdl:service>
</wsdl:definitions>]]></con:content><con:type>http://schemas.xmlsoap.org/wsdl/</con:type></con:part></con:definitionCache><con:endpoints><con:endpoint>http://localhost:8082/axis2/services/EmployeeManagementService.EmployeeManagementServiceHttpSoap12Endpoint/</con:endpoint></con:endpoints><con:operation id="123519c1-7bd6-47ab-9953-402866013851" isOneWay="false" action="urn:addEmployee" name="addEmployee" bindingOperationName="addEmployee" type="Request-Response" inputName="" receivesAttachments="false" sendsAttachments="false" anonymous="optional"><con:settings/><con:call id="c6a3d3b3-0909-4b50-a745-9413e40e66e4" name="Request 1"><con:settings/><con:encoding>UTF-8</con:encoding><con:endpoint>http://localhost:8082/axis2/services/EmployeeManagementService.EmployeeManagementServiceHttpSoap12Endpoint/</con:endpoint><con:request><![CDATA[<soap:Envelope xmlns:soap="http://www.w3.org/2003/05/soap-envelope" xmlns:typ="http://sample.com/reservation/guest/types">\r
   <soap:Header/>\r
   <soap:Body>\r
      <typ:addEmployee>\r
         <!--Optional:-->\r
         <typ:name>?</typ:name>\r
         <!--Optional:-->\r
         <typ:id>?</typ:id>\r
         <!--Optional:-->\r
         <typ:Department>?</typ:Department>\r
         <!--Optional:-->\r
         <typ:age>?</typ:age>\r
      </typ:addEmployee>\r
   </soap:Body>\r
</soap:Envelope>]]></con:request><con:credentials><con:authType>No Authorization</con:authType></con:credentials><con:jmsConfig JMSDeliveryMode="PERSISTENT"/><con:jmsPropertyConfig/><con:wsaConfig mustUnderstand="NONE" version="200508" action="urn:addEmployee"/><con:wsrmConfig version="1.2"/></con:call></con:operation><con:operation id="74590821-6ab9-438e-89af-66e2b52f81f0" isOneWay="false" action="urn:deleteEmployee" name="deleteEmployee" bindingOperationName="deleteEmployee" type="One-Way" inputName="" sendsAttachments="false" anonymous="optional"><con:settings/><con:call id="e3fd8ecd-b903-4e3d-974c-8cd79c3905fc" name="Request 1"><con:settings/><con:encoding>UTF-8</con:encoding><con:endpoint>http://localhost:8082/axis2/services/EmployeeManagementService.EmployeeManagementServiceHttpSoap12Endpoint/</con:endpoint><con:request><![CDATA[<soap:Envelope xmlns:soap="http://www.w3.org/2003/05/soap-envelope" xmlns:typ="http://sample.com/reservation/guest/types">\r
   <soap:Header/>\r
   <soap:Body>\r
      <typ:deleteEmployee>\r
         <!--Optional:-->\r
         <typ:employeeName>?</typ:employeeName>\r
      </typ:deleteEmployee>\r
   </soap:Body>\r
</soap:Envelope>]]></con:request><con:credentials><con:authType>No Authorization</con:authType></con:credentials><con:jmsConfig JMSDeliveryMode="PERSISTENT"/><con:jmsPropertyConfig/><con:wsaConfig mustUnderstand="NONE" version="200508" action="urn:deleteEmployee"/><con:wsrmConfig version="1.2"/></con:call></con:operation><con:operation id="9f92e568-1bd0-4313-9039-602e17235540" isOneWay="false" action="urn:getEmployeeDetails" name="getEmployeeDetails" bindingOperationName="getEmployeeDetails" type="Request-Response" inputName="" receivesAttachments="false" sendsAttachments="false" anonymous="optional"><con:settings/><con:call id="d84c3b1d-ab23-4630-a8a3-1f16186a2046" name="Request 1"><con:settings/><con:encoding>UTF-8</con:encoding><con:endpoint>http://localhost:8082/axis2/services/EmployeeManagementService.EmployeeManagementServiceHttpSoap12Endpoint/</con:endpoint><con:request><![CDATA[<soap:Envelope xmlns:soap="http://www.w3.org/2003/05/soap-envelope" xmlns:typ="http://sample.com/reservation/guest/types">\r
   <soap:Header/>\r
   <soap:Body>\r
      <typ:getEmployeeDetails>\r
         <!--Optional:-->\r
         <typ:employeeName>?</typ:employeeName>\r
      </typ:getEmployeeDetails>\r
   </soap:Body>\r
</soap:Envelope>]]></con:request><con:jmsConfig JMSDeliveryMode="PERSISTENT"/><con:wsaConfig mustUnderstand="NONE" version="200508" action="urn:getEmployeeDetails"/></con:call></con:operation></con:interface><con:interface xsi:type="con:WsdlInterface" id="de5ef7d8-69ca-4934-8f36-7d6a16bcd04f" wsaVersion="NONE" name="EmployeeManagementServiceSoap11Binding" type="wsdl" bindingName="{http://sample.com/reservation/guest}EmployeeManagementServiceSoap11Binding" soapVersion="1_1" anonymous="optional" definition="http://localhost:8082/axis2/services/EmployeeManagementService?wsdl" xmlns:xsi="http://www.w3.org/2001/XMLSchema-instance"><con:settings/><con:definitionCache type="TEXT" rootPart="http://localhost:8082/axis2/services/EmployeeManagementService?wsdl"><con:part><con:url>http://localhost:8082/axis2/services/EmployeeManagementService?wsdl</con:url><con:content><![CDATA[<wsdl:definitions targetNamespace="http://sample.com/reservation/guest" xmlns:wsdl="http://schemas.xmlsoap.org/wsdl/" xmlns:ns="http://sample.com/reservation/guest/types" xmlns:wsaw="http://www.w3.org/2006/05/addressing/wsdl" xmlns:mime="http://schemas.xmlsoap.org/wsdl/mime/" xmlns:tns="http://sample.com/reservation/guest" xmlns:http="http://schemas.xmlsoap.org/wsdl/http/" xmlns:xs="http://www.w3.org/2001/XMLSchema" xmlns:ax21="http://exception.reservation.sample.com/xsd" xmlns:soap12="http://schemas.xmlsoap.org/wsdl/soap12/" xmlns:ns1="http://org.apache.axis2/xsd" xmlns:soap="http://schemas.xmlsoap.org/wsdl/soap/">
  <wsdl:documentation>EmployeeManagementService</wsdl:documentation>
  <wsdl:types>
    <xs:schema attributeFormDefault="qualified" elementFormDefault="qualified" targetNamespace="http://exception.reservation.sample.com/xsd">
      <xs:complexType name="EmployeeManagementException">
        <xs:sequence>
          <xs:element minOccurs="0" name="message" nillable="true" type="xs:string"/>
        </xs:sequence>
      </xs:complexType>
    </xs:schema>
    <xs:schema attributeFormDefault="qualified" elementFormDefault="qualified" targetNamespace="http://sample.com/reservation/guest/types" xmlns:ax22="http://exception.reservation.sample.com/xsd">
      <xs:import namespace="http://exception.reservation.sample.com/xsd"/>
      <xs:element name="EmployeeManagementServiceEmployeeManagementException">
        <xs:complexType>
          <xs:sequence>
            <xs:element minOccurs="0" name="EmployeeManagementException" nillable="true" type="ax22:EmployeeManagementException"/>
          </xs:sequence>
        </xs:complexType>
      </xs:element>
      <xs:element name="addEmployee">
        <xs:complexType>
          <xs:sequence>
            <xs:element minOccurs="0" name="name" nillable="true" type="xs:string"/>
            <xs:element minOccurs="0" name="id" nillable="true" type="xs:string"/>
            <xs:element minOccurs="0" name="Department" nillable="true" type="xs:string"/>
            <xs:element minOccurs="0" name="age" type="xs:int"/>
          </xs:sequence>
        </xs:complexType>
      </xs:element>
      <xs:element name="addEmployeeResponse">
        <xs:complexType>
          <xs:sequence>
            <xs:element minOccurs="0" name="return" type="xs:boolean"/>
          </xs:sequence>
        </xs:complexType>
      </xs:element>
      <xs:element name="deleteEmployee">
        <xs:complexType>
          <xs:sequence>
            <xs:element minOccurs="0" name="employeeName" nillable="true" type="xs:string"/>
          </xs:sequence>
        </xs:complexType>
      </xs:element>
      <xs:element name="getEmployeeDetails">
        <xs:complexType>
          <xs:sequence>
            <xs:element minOccurs="0" name="employeeName" nillable="true" type="xs:string"/>
          </xs:sequence>
        </xs:complexType>
      </xs:element>
      <xs:element name="getEmployeeDetailsResponse">
        <xs:complexType>
          <xs:sequence>
            <xs:element minOccurs="0" name="return" nillable="true" type="ns:Employee"/>
          </xs:sequence>
        </xs:complexType>
      </xs:element>
      <xs:complexType name="Employee">
        <xs:sequence>
          <xs:element minOccurs="0" name="age" type="xs:int"/>
          <xs:element minOccurs="0" name="department" nillable="true" type="xs:string"/>
          <xs:element minOccurs="0" name="id" nillable="true" type="xs:string"/>
          <xs:element minOccurs="0" name="name" nillable="true" type="xs:string"/>
        </xs:sequence>
      </xs:complexType>
    </xs:schema>
  </wsdl:types>
  <wsdl:message name="getEmployeeDetailsRequest">
    <wsdl:part name="parameters" element="ns:getEmployeeDetails"/>
  </wsdl:message>
  <wsdl:message name="getEmployeeDetailsResponse">
    <wsdl:part name="parameters" element="ns:getEmployeeDetailsResponse"/>
  </wsdl:message>
  <wsdl:message name="EmployeeManagementServiceEmployeeManagementException">
    <wsdl:part name="parameters" element="ns:EmployeeManagementServiceEmployeeManagementException"/>
  </wsdl:message>
  <wsdl:message name="deleteEmployeeRequest">
    <wsdl:part name="parameters" element="ns:deleteEmployee"/>
  </wsdl:message>
  <wsdl:message name="addEmployeeRequest">
    <wsdl:part name="parameters" element="ns:addEmployee"/>
  </wsdl:message>
  <wsdl:message name="addEmployeeResponse">
    <wsdl:part name="parameters" element="ns:addEmployeeResponse"/>
  </wsdl:message>
  <wsdl:portType name="EmployeeManagementServicePortType">
    <wsdl:operation name="getEmployeeDetails">
      <wsdl:input message="tns:getEmployeeDetailsRequest" wsaw:Action="urn:getEmployeeDetails"/>
      <wsdl:output message="tns:getEmployeeDetailsResponse" wsaw:Action="urn:getEmployeeDetailsResponse"/>
      <wsdl:fault message="tns:EmployeeManagementServiceEmployeeManagementException" name="EmployeeManagementServiceEmployeeManagementException" wsaw:Action="urn:getEmployeeDetailsEmployeeManagementServiceEmployeeManagementException"/>
    </wsdl:operation>
    <wsdl:operation name="deleteEmployee">
      <wsdl:input message="tns:deleteEmployeeRequest" wsaw:Action="urn:deleteEmployee"/>
      <wsdl:fault message="tns:EmployeeManagementServiceEmployeeManagementException" name="EmployeeManagementServiceEmployeeManagementException" wsaw:Action="urn:deleteEmployeeEmployeeManagementServiceEmployeeManagementException"/>
    </wsdl:operation>
    <wsdl:operation name="addEmployee">
      <wsdl:input message="tns:addEmployeeRequest" wsaw:Action="urn:addEmployee"/>
      <wsdl:output message="tns:addEmployeeResponse" wsaw:Action="urn:addEmployeeResponse"/>
      <wsdl:fault message="tns:EmployeeManagementServiceEmployeeManagementException" name="EmployeeManagementServiceEmployeeManagementException" wsaw:Action="urn:addEmployeeEmployeeManagementServiceEmployeeManagementException"/>
    </wsdl:operation>
  </wsdl:portType>
  <wsdl:binding name="EmployeeManagementServiceSoap11Binding" type="tns:EmployeeManagementServicePortType">
    <soap:binding transport="http://schemas.xmlsoap.org/soap/http" style="document"/>
    <wsdl:operation name="getEmployeeDetails">
      <soap:operation soapAction="urn:getEmployeeDetails" style="document"/>
      <wsdl:input>
        <soap:body use="literal"/>
      </wsdl:input>
      <wsdl:output>
        <soap:body use="literal"/>
      </wsdl:output>
      <wsdl:fault name="EmployeeManagementServiceEmployeeManagementException">
        <soap:fault use="literal" name="EmployeeManagementServiceEmployeeManagementException"/>
      </wsdl:fault>
    </wsdl:operation>
    <wsdl:operation name="deleteEmployee">
      <soap:operation soapAction="urn:deleteEmployee" style="document"/>
      <wsdl:input>
        <soap:body use="literal"/>
      </wsdl:input>
      <wsdl:fault name="EmployeeManagementServiceEmployeeManagementException">
        <soap:fault use="literal" name="EmployeeManagementServiceEmployeeManagementException"/>
      </wsdl:fault>
    </wsdl:operation>
    <wsdl:operation name="addEmployee">
      <soap:operation soapAction="urn:addEmployee" style="document"/>
      <wsdl:input>
        <soap:body use="literal"/>
      </wsdl:input>
      <wsdl:output>
        <soap:body use="literal"/>
      </wsdl:output>
      <wsdl:fault name="EmployeeManagementServiceEmployeeManagementException">
        <soap:fault use="literal" name="EmployeeManagementServiceEmployeeManagementException"/>
      </wsdl:fault>
    </wsdl:operation>
  </wsdl:binding>
  <wsdl:binding name="EmployeeManagementServiceSoap12Binding" type="tns:EmployeeManagementServicePortType">
    <soap12:binding transport="http://schemas.xmlsoap.org/soap/http" style="document"/>
    <wsdl:operation name="getEmployeeDetails">
      <soap12:operation soapAction="urn:getEmployeeDetails" style="document"/>
      <wsdl:input>
        <soap12:body use="literal"/>
      </wsdl:input>
      <wsdl:output>
        <soap12:body use="literal"/>
      </wsdl:output>
      <wsdl:fault name="EmployeeManagementServiceEmployeeManagementException">
        <soap12:fault use="literal" name="EmployeeManagementServiceEmployeeManagementException"/>
      </wsdl:fault>
    </wsdl:operation>
    <wsdl:operation name="deleteEmployee">
      <soap12:operation soapAction="urn:deleteEmployee" style="document"/>
      <wsdl:input>
        <soap12:body use="literal"/>
      </wsdl:input>
      <wsdl:fault name="EmployeeManagementServiceEmployeeManagementException">
        <soap12:fault use="literal" name="EmployeeManagementServiceEmployeeManagementException"/>
      </wsdl:fault>
    </wsdl:operation>
    <wsdl:operation name="addEmployee">
      <soap12:operation soapAction="urn:addEmployee" style="document"/>
      <wsdl:input>
        <soap12:body use="literal"/>
      </wsdl:input>
      <wsdl:output>
        <soap12:body use="literal"/>
      </wsdl:output>
      <wsdl:fault name="EmployeeManagementServiceEmployeeManagementException">
        <soap12:fault use="literal" name="EmployeeManagementServiceEmployeeManagementException"/>
      </wsdl:fault>
    </wsdl:operation>
  </wsdl:binding>
  <wsdl:binding name="EmployeeManagementServiceHttpBinding" type="tns:EmployeeManagementServicePortType">
    <http:binding verb="POST"/>
    <wsdl:operation name="getEmployeeDetails">
      <http:operation location="getEmployeeDetails"/>
      <wsdl:input>
        <mime:content type="application/xml" part="parameters"/>
      </wsdl:input>
      <wsdl:output>
        <mime:content type="application/xml" part="parameters"/>
      </wsdl:output>
    </wsdl:operation>
    <wsdl:operation name="deleteEmployee">
      <http:operation location="deleteEmployee"/>
      <wsdl:input>
        <mime:content type="application/xml" part="parameters"/>
      </wsdl:input>
    </wsdl:operation>
    <wsdl:operation name="addEmployee">
      <http:operation location="addEmployee"/>
      <wsdl:input>
        <mime:content type="application/xml" part="parameters"/>
      </wsdl:input>
      <wsdl:output>
        <mime:content type="application/xml" part="parameters"/>
      </wsdl:output>
    </wsdl:operation>
  </wsdl:binding>
  <wsdl:service name="EmployeeManagementService">
    <wsdl:port name="EmployeeManagementServiceHttpSoap11Endpoint" binding="tns:EmployeeManagementServiceSoap11Binding">
      <soap:address location="http://localhost:8082/axis2/services/EmployeeManagementService.EmployeeManagementServiceHttpSoap11Endpoint/"/>
    </wsdl:port>
    <wsdl:port name="EmployeeManagementServiceHttpSoap12Endpoint" binding="tns:EmployeeManagementServiceSoap12Binding">
      <soap12:address location="http://localhost:8082/axis2/services/EmployeeManagementService.EmployeeManagementServiceHttpSoap12Endpoint/"/>
    </wsdl:port>
    <wsdl:port name="EmployeeManagementServiceHttpEndpoint" binding="tns:EmployeeManagementServiceHttpBinding">
      <http:address location="http://localhost:8082/axis2/services/EmployeeManagementService.EmployeeManagementServiceHttpEndpoint/"/>
    </wsdl:port>
  </wsdl:service>
</wsdl:definitions>]]></con:content><con:type>http://schemas.xmlsoap.org/wsdl/</con:type></con:part></con:definitionCache><con:endpoints><con:endpoint>http://localhost:8082/axis2/services/EmployeeManagementService.EmployeeManagementServiceHttpSoap11Endpoint/</con:endpoint></con:endpoints><con:operation id="e1283db6-ac4b-42a3-a7de-863fe94a807a" isOneWay="false" action="urn:addEmployee" name="addEmployee" bindingOperationName="addEmployee" type="Request-Response" inputName="" receivesAttachments="false" sendsAttachments="false" anonymous="optional"><con:settings/><con:call id="098c601d-8f2a-47d1-987b-f716e0987895" name="Request 1"><con:settings><con:setting id="com.eviware.soapui.impl.wsdl.WsdlRequest@request-headers">&lt;xml-fragment/></con:setting></con:settings><con:encoding>UTF-8</con:encoding><con:endpoint>http://localhost:8082/axis2/services/EmployeeManagementService.EmployeeManagementServiceHttpSoap11Endpoint/</con:endpoint><con:request><![CDATA[<soapenv:Envelope xmlns:soapenv="http://schemas.xmlsoap.org/soap/envelope/" xmlns:typ="http://sample.com/reservation/guest/types">\r
   <soapenv:Header/>\r
   <soapenv:Body>\r
      <typ:addEmployee>\r
         <!--Optional:-->\r
         <typ:name>Bhargav</typ:name>\r
         <!--Optional:-->\r
         <typ:id>234</typ:id>\r
         <!--Optional:-->\r
         <typ:Department>egerg</typ:Department>\r
         <!--Optional:-->\r
         <typ:age>32</typ:age>\r
      </typ:addEmployee>\r
   </soapenv:Body>\r
</soapenv:Envelope>]]></con:request><con:credentials><con:authType>No Authorization</con:authType></con:credentials><con:jmsConfig JMSDeliveryMode="PERSISTENT"/><con:jmsPropertyConfig/><con:wsaConfig mustUnderstand="NONE" version="200508" action="urn:addEmployee"/><con:wsrmConfig version="1.2"/></con:call></con:operation><con:operation id="ccf59311-a531-40a6-8614-86ffd68ca885" isOneWay="false" action="urn:deleteEmployee" name="deleteEmployee" bindingOperationName="deleteEmployee" type="One-Way" inputName="" sendsAttachments="false" anonymous="optional"><con:settings/><con:call id="4118dfce-36fa-41a0-8c0e-2c770a5b1e5e" name="Request 1"><con:settings/><con:encoding>UTF-8</con:encoding><con:endpoint>http://localhost:8082/axis2/services/EmployeeManagementService.EmployeeManagementServiceHttpSoap11Endpoint/</con:endpoint><con:request><![CDATA[<soapenv:Envelope xmlns:soapenv="http://schemas.xmlsoap.org/soap/envelope/" xmlns:typ="http://sample.com/reservation/guest/types">\r
   <soapenv:Header/>\r
   <soapenv:Body>\r
      <typ:deleteEmployee>\r
         <!--Optional:-->\r
         <typ:employeeName>?</typ:employeeName>\r
      </typ:deleteEmployee>\r
   </soapenv:Body>\r
</soapenv:Envelope>]]></con:request><con:jmsConfig JMSDeliveryMode="PERSISTENT"/><con:wsaConfig mustUnderstand="NONE" version="200508" action="urn:deleteEmployee"/></con:call></con:operation><con:operation id="62eb9f6d-1758-4740-8af8-d3d0490f1f19" isOneWay="false" action="urn:getEmployeeDetails" name="getEmployeeDetails" bindingOperationName="getEmployeeDetails" type="Request-Response" inputName="" receivesAttachments="false" sendsAttachments="false" anonymous="optional"><con:settings/><con:call id="7517440b-d0f0-4f1e-a3b8-f0a611cdb539" name="Request 1"><con:settings/><con:encoding>UTF-8</con:encoding><con:endpoint>http://localhost:8082/axis2/services/EmployeeManagementService.EmployeeManagementServiceHttpSoap11Endpoint/</con:endpoint><con:request><![CDATA[<soapenv:Envelope xmlns:soapenv="http://schemas.xmlsoap.org/soap/envelope/" xmlns:typ="http://sample.com/reservation/guest/types">\r
   <soapenv:Header/>\r
   <soapenv:Body>\r
      <typ:getEmployeeDetails>\r
         <!--Optional:-->\r
         <typ:employeeName>?</typ:employeeName>\r
      </typ:getEmployeeDetails>\r
   </soapenv:Body>\r
</soapenv:Envelope>]]></con:request><con:credentials><con:authType>No Authorization</con:authType></con:credentials><con:jmsConfig JMSDeliveryMode="PERSISTENT"/><con:jmsPropertyConfig/><con:wsaConfig mustUnderstand="NONE" version="200508" action="urn:getEmployeeDetails"/><con:wsrmConfig version="1.2"/></con:call></con:operation></con:interface><con:testSuite id="1c26aa43-8311-4f32-a145-ea85b32568e9" name="TestSuiteAssertion"><con:settings/><con:runType>SEQUENTIAL</con:runType><con:testCase id="4118ba23-a9a4-4acc-a9a4-6d1aa59dd0f3" failOnError="true" failTestCaseOnErrors="true" keepSession="false" maxResults="0" name="E2E" searchProperties="true"><con:settings/><con:testStep type="request" name="Soap1" id="36fdd876-6434-493c-8457-f8c06edc5c75"><con:settings/><con:config xsi:type="con:RequestStep" xmlns:xsi="http://www.w3.org/2001/XMLSchema-instance"><con:interface>EmployeeManagementServiceSoap12Binding</con:interface><con:operation>addEmployee</con:operation><con:request name="Soap1" id="50a4ee11-c529-4107-a394-dd3fbf40e41b"><con:settings><con:setting id="com.eviware.soapui.impl.wsdl.WsdlRequest@request-headers">&lt;xml-fragment/></con:setting></con:settings><con:encoding>UTF-8</con:encoding><con:endpoint>http://localhost:8082/axis2/services/EmployeeManagementService.EmployeeManagementServiceHttpSoap12Endpoint/</con:endpoint><con:request><![CDATA[<soap:Envelope xmlns:soap="http://www.w3.org/2003/05/soap-envelope" xmlns:typ="http://sample.com/reservation/guest/types">
   <soap:Header/>
   <soap:Body>
      <typ:addEmployee>
         <!--Optional:-->
         <typ:name>groovyTetstRunner</typ:name>
         <!--Optional:-->
         <typ:id>89759873</typ:id>
         <!--Optional:-->
         <typ:Department>groovyDep</typ:Department>
         <!--Optional:-->
         <typ:age>45</typ:age>
      </typ:addEmployee>
   </soap:Body>
</soap:Envelope>]]></con:request><con:assertion type="SOAP Response" id="f29796f9-3d23-4836-99d5-d9645c10c181"/><con:credentials><con:authType>No Authorization</con:authType></con:credentials><con:jmsConfig JMSDeliveryMode="PERSISTENT"/><con:jmsPropertyConfig/><con:wsaConfig mustUnderstand="NONE" version="200508"/><con:wsrmConfig version="1.2"/></con:request></con:config></con:testStep><con:testStep type="groovy" name="Groovy Scriptrunner" id="814639e5-080f-4ba8-931f-e90d25123170"><con:settings/><con:config><script>import com.eviware.soapui.support.XmlHolder
import com.eviware.soapui.impl.wsdl.testcase.WsdlTestRunContext
def addReq= testRunner.testCase.testSuite.testCases["E2E"].testSteps["Soap1"].getPropertyValue("Request")
def id=testRunner.testCase.getPropertyValue("id")
def deppart=testRunner.testCase.getPropertyValue("department")
def names=testRunner.testCase.testSuite.getPropertyValue("names")
def age=testRunner.testCase.getPropertyValue("age")
def xmlAdd=new XmlHolder(addReq)
////typ:addEmployee/typ:name/typ:id/typ:Department
xmlAdd.setNodeValue("//typ:addEmployee/typ:name",names)
xmlAdd.setNodeValue("//typ:addEmployee/typ:id",id)
xmlAdd.setNodeValue("//typ:addEmployee/typ:Department",deppart)
xmlAdd.setNodeValue("//typ:addEmployee/typ:age",age)
def UpdAddXml=xmlAdd.getXml();
testRunner.testCase.testSuite.testCases["E2E"].testSteps["Soap1"].setPropertyValue("Request",UpdAddXml)
def addtestStep=testRunner.testCase.testSuite.testCases["E2E"].testSteps["Soap1"]
def contextAdd=new WsdlTestRunContext(addtestStep)
addtestStep.run(testRunner,contextAdd)</script></con:config></con:testStep><con:testStep type="groovy" name="Groovy Script1" id="e85cd2a7-bd43-4319-9f80-ea79dc6e751e"><con:settings/><con:config><script>log.info "my first Groovy"
log.info context.expand('${#TestCase#groovyKey}')
//log.info context.expand('${#TestCase#getFrom}') wont work
//below to get property from other tc's of same suite
log.info testRunner.testCase.testSuite.testCases["get"].getPropertyValue("getFrom")
//below to get value from same tc of same suite
log.info testRunner.testCase.getPropertyValue("groovyKey")
//to get values from testStep 
log.info testRunner.testCase.testSuite.testCases["get"].testSteps["getting"].getPropertyValue("Request")
log.info testRunner.testCase.testSuite.testCases["delete"].testSteps["deleteStep"].getPropertyValue("Request")
//from same testStep of same tc
log.info testRunner.testCase.testSteps["Soap1"].getPropertyValue("Request")
//to set property in test cases
//set for same tc
testRunner.testCase.setPropertyValue("setter","xcs123")
//set for different tc
testRunner.testCase.testSuite.testCases["delete"].setPropertyValue("settingDelete","565755776")
def proj=testRunner.testCase.testSuite.project
log.info proj.getPropertyValue("ProjectLevel")
def xmlAdd=new xmlHolder(Soap1)
xmlAdd.setMethodValue(</script></con:config></con:testStep><con:testStep type="properties" name="BhaProperties1" id="83adf269-2b64-4929-9d84-b71cd9e63519"><con:settings/><con:config xsi:type="con:PropertiesStep" saveFirst="true" xmlns:xsi="http://www.w3.org/2001/XMLSchema-instance"><con:properties><con:property><con:name>department</con:name><con:value>cdsjhh</con:value></con:property></con:properties></con:config></con:testStep><con:testStep type="request" name="getting" id="e8f1a3df-7a2d-4285-a2b4-b162f31755d4"><con:settings/><con:config xsi:type="con:RequestStep" xmlns:xsi="http://www.w3.org/2001/XMLSchema-instance"><con:interface>EmployeeManagementServiceSoap11Binding</con:interface><con:operation>getEmployeeDetails</con:operation><con:request name="getting" id="6d3605f3-6821-4567-a631-a9e02b069490"><con:settings><con:setting id="com.eviware.soapui.impl.wsdl.WsdlRequest@request-headers">&lt;xml-fragment/></con:setting></con:settings><con:encoding>UTF-8</con:encoding><con:endpoint>http://localhost:8082/axis2/services/EmployeeManagementService.EmployeeManagementServiceHttpSoap11Endpoint/</con:endpoint><con:request><![CDATA[<soapenv:Envelope xmlns:soapenv="http://schemas.xmlsoap.org/soap/envelope/" xmlns:typ="http://sample.com/reservation/guest/types">
   <soapenv:Header/>
   <soapenv:Body>
      <typ:getEmployeeDetails>
         <!--Optional:-->
         <typ:employeeName>groovyTetstRunner</typ:employeeName>
      </typ:getEmployeeDetails>
   </soapenv:Body>
</soapenv:Envelope>]]></con:request><con:assertion type="SOAP Response" id="6e1a579c-0091-4b95-9fb3-606d46e3c08e"/><con:credentials><con:authType>No Authorization</con:authType></con:credentials><con:jmsConfig JMSDeliveryMode="PERSISTENT"/><con:jmsPropertyConfig/><con:wsaConfig mustUnderstand="NONE" version="200508"/><con:wsrmConfig version="1.2"/></con:request></con:config></con:testStep><con:testStep type="groovy" name="GroovyGetEmpDetails" id="c95a3299-cfde-4735-9860-04bceefd4ef3"><con:settings/><con:config><script>import com.eviware.soapui.support.XmlHolder
import com.eviware.soapui.impl.wsdl.testcase.WsdlTestRunContext
def getXml=testRunner.testCase.testSuite.testCases["E2E"].testSteps["getting"].getPropertyValue("Request")
def name=testRunner.testCase.testSuite.getPropertyValue("names")
def age= testRunner.testCase.testSuite.getPropertyValue("age")
def getXmlHolder=new XmlHolder(getXml)
getXmlHolder.setNodeValue("//typ:getEmployeeDetails/typ:employeeName",name)
def updXml=getXmlHolder.getXml();
testRunner.testCase.testSuite.testCases["E2E"].testSteps["getting"].setPropertyValue("Request",updXml)
def getStep=testRunner.testCase.testSuite.testCases["E2E"].testSteps["getting"]
def getContext=new WsdlTestRunContext(getStep)
getStep.run(testRunner,getContext)

def resp=testRunner.testCase.testSuite.testCases["E2E"].testSteps["getting"].getPropertyValue("Response")
def getHolder=new XmlHolder(resp)
def resName=getHolder.getNodeValue("//ns:name")
//log.info name
//assert resName=="groovyTetstRunner"
assert resName==name</script></con:config></con:testStep><con:testStep type="transfer" name="Property Transfer" id="e79f563c-3321-4649-9114-f10b83ed5363"><con:settings/><con:config xsi:type="con:PropertyTransfersStep" xmlns:xsi="http://www.w3.org/2001/XMLSchema-instance"><con:transfers setNullOnMissingSource="true" transferTextContent="true" failOnError="true" ignoreEmpty="false" transferToAll="false" entitize="false" transferChildNodes="false"><con:name>traff</con:name><con:sourceType>Response</con:sourceType><con:sourceStep>getting</con:sourceStep><con:sourcePath>declare namespace ns='http://sample.com/reservation/guest/types';
//ns:getEmployeeDetailsResponse/ns:return/ns:name/text()</con:sourcePath><con:targetType xsi:nil="true"/><con:targetStep>getting</con:targetStep><con:targetPath>declare namespace typ='http://sample.com/reservation/guest/types'
//typ:employeeName</con:targetPath><con:upgraded>true</con:upgraded></con:transfers></con:config></con:testStep><con:testStep type="groovy" name="GroovyScriptTcrunning" id="7ad80e07-03b2-47a2-aa3c-c914c3e86273"><con:settings/><con:config><script/></con:config></con:testStep><con:testStep type="request" name="Delete" id="b9fc8d70-49e4-450a-8027-a236cfd6e99a"><con:settings/><con:config xsi:type="con:RequestStep" xmlns:xsi="http://www.w3.org/2001/XMLSchema-instance"><con:interface>EmployeeManagementServiceSoap12Binding</con:interface><con:operation>deleteEmployee</con:operation><con:request name="Delete" id="3db4dea2-be5f-4ffc-9103-2d137b826e30"><con:settings><con:setting id="com.eviware.soapui.impl.wsdl.WsdlRequest@request-headers">&lt;xml-fragment/></con:setting></con:settings><con:encoding>UTF-8</con:encoding><con:endpoint>http://localhost:8082/axis2/services/EmployeeManagementService.EmployeeManagementServiceHttpSoap12Endpoint/</con:endpoint><con:request><![CDATA[<soap:Envelope xmlns:soap="http://www.w3.org/2003/05/soap-envelope" xmlns:typ="http://sample.com/reservation/guest/types">\r
   <soap:Header/>\r
   <soap:Body>\r
      <typ:addEmployee>\r
         <!--Optional:-->\r
         <typ:name>groovyTetstRunner</typ:name>\r
         <!--Optional:-->\r
         <typ:id>?</typ:id>\r
         <!--Optional:-->\r
         <typ:Department>?</typ:Department>\r
         <!--Optional:-->\r
         <typ:age>?</typ:age>\r
      </typ:addEmployee>\r
   </soap:Body>\r
</soap:Envelope>]]></con:request><con:assertion type="SOAP Response" id="9bf03144-929e-4c1e-b200-173cc1d2915f"/><con:credentials><con:authType>No Authorization</con:authType></con:credentials><con:jmsConfig JMSDeliveryMode="PERSISTENT"/><con:jmsPropertyConfig/><con:wsaConfig mustUnderstand="NONE" version="200508"/><con:wsrmConfig version="1.2"/></con:request></con:config></con:testStep><con:properties><con:property><con:name>id</con:name><con:value>89759873</con:value></con:property><con:property><con:name>department</con:name><con:value>groovyDep</con:value></con:property><con:property><con:name>groovyKey</con:name><con:value>GroovyValue</con:value></con:property><con:property><con:name>setter</con:name><con:value>xcs123</con:value></con:property><con:property><con:name>age</con:name><con:value>45</con:value></con:property></con:properties><con:securityTest id="74371847-455b-4a8b-b107-64eabddacd06" name="SecurityTest 1" failOnError="true"><con:settings/><con:properties/></con:securityTest><con:securityTest id="8bbf524c-a25f-4441-8937-100fcdcc96fb" name="SecurityTest 2" failOnError="true"><con:settings/><con:properties/></con:securityTest></con:testCase><con:testCase id="e5d30f9f-c2ba-4622-9d8c-fe25092b7878" failOnError="true" failTestCaseOnErrors="true" keepSession="false" maxResults="0" name="get" searchProperties="true"><con:settings/><con:testStep type="request" name="getting" id="8e028983-f203-476d-8b19-deb3f2d4d450"><con:settings/><con:config xsi:type="con:RequestStep" xmlns:xsi="http://www.w3.org/2001/XMLSchema-instance"><con:interface>EmployeeManagementServiceSoap11Binding</con:interface><con:operation>getEmployeeDetails</con:operation><con:request name="getting" id="6d3605f3-6821-4567-a631-a9e02b069490"><con:settings><con:setting id="com.eviware.soapui.impl.wsdl.WsdlRequest@request-headers">&lt;xml-fragment/></con:setting></con:settings><con:encoding>UTF-8</con:encoding><con:endpoint>http://localhost:8082/axis2/services/EmployeeManagementService.EmployeeManagementServiceHttpSoap11Endpoint/</con:endpoint><con:request><![CDATA[<soapenv:Envelope xmlns:soapenv="http://schemas.xmlsoap.org/soap/envelope/" xmlns:typ="http://sample.com/reservation/guest/types">\r
   <soapenv:Header/>\r
   <soapenv:Body>\r
      <typ:getEmployeeDetails>\r
         <!--Optional:-->\r
         <typ:employeeName>${#Project#name}</typ:employeeName>\r
      </typ:getEmployeeDetails>\r
   </soapenv:Body>\r
</soapenv:Envelope>]]></con:request><con:assertion type="SOAP Response" id="6e1a579c-0091-4b95-9fb3-606d46e3c08e"/><con:credentials><con:authType>No Authorization</con:authType></con:credentials><con:jmsConfig JMSDeliveryMode="PERSISTENT"/><con:jmsPropertyConfig/><con:wsaConfig mustUnderstand="NONE" version="200508"/><con:wsrmConfig version="1.2"/></con:request></con:config></con:testStep><con:properties><con:property><con:name>name</con:name><con:value>soap</con:value></con:property><con:property><con:name>getFrom</con:name><con:value>6565</con:value></con:property></con:properties></con:testCase><con:testCase id="0cefb36c-0aee-40af-8028-138c1cba6307" failOnError="true" failTestCaseOnErrors="true" keepSession="false" maxResults="0" name="delete" searchProperties="true"><con:settings/><con:testStep type="request" name="deleteStep" id="ba9867f7-7db4-45a8-a459-61b9dd047ade"><con:settings/><con:config xsi:type="con:RequestStep" xmlns:xsi="http://www.w3.org/2001/XMLSchema-instance"><con:interface>EmployeeManagementServiceSoap11Binding</con:interface><con:operation>deleteEmployee</con:operation><con:request name="deleteStep" id="b6a57f67-cb7f-4499-9636-6f458125e1ec"><con:settings><con:setting id="com.eviware.soapui.impl.wsdl.WsdlRequest@request-headers">&lt;xml-fragment/></con:setting></con:settings><con:encoding>UTF-8</con:encoding><con:endpoint>http://localhost:8082/axis2/services/EmployeeManagementService.EmployeeManagementServiceHttpSoap11Endpoint/</con:endpoint><con:request><![CDATA[<soapenv:Envelope xmlns:soapenv="http://schemas.xmlsoap.org/soap/envelope/" xmlns:typ="http://sample.com/reservation/guest/types">\r
   <soapenv:Header/>\r
   <soapenv:Body>\r
      <typ:deleteEmployee>\r
         <!--Optional:-->\r
         <typ:employeeName>soap</typ:employeeName>\r
      </typ:deleteEmployee>\r
   </soapenv:Body>\r
</soapenv:Envelope>]]></con:request><con:assertion type="SOAP Response" id="38d2094d-d64d-4283-91fd-ae9a9a450992"/><con:credentials><con:authType>No Authorization</con:authType></con:credentials><con:jmsConfig JMSDeliveryMode="PERSISTENT"/><con:jmsPropertyConfig/><con:wsaConfig mustUnderstand="NONE" version="200508"/><con:wsrmConfig version="1.2"/></con:request></con:config></con:testStep><con:properties><con:property><con:name>settingDelete</con:name><con:value>565755776</con:value></con:property></con:properties></con:testCase><con:properties><con:property><con:name>age</con:name><con:value>23</con:value></con:property><con:property><con:name>names</con:name><con:value>groovyTetstRunner</con:value></con:property><con:property><con:name>department</con:name><con:value>dsvsdv</con:value></con:property></con:properties></con:testSuite><con:properties><con:property><con:name>name</con:name><con:value>suitelevelnamefegrgrt</con:value></con:property><con:property><con:name>ProjectLevel</con:name><con:value>projectLevel123</con:value></con:property></con:properties><con:wssContainer/><con:oAuth2ProfileContainer/><con:oAuth1ProfileContainer/><con:sensitiveInformation/></con:soapui-project>